sipay/__init__.py
sipay/amount.py
sipay/logger.py
sipay/catalogs/__init__.py
sipay/catalogs/currency.py
sipay/ecommerce/__init__.py
sipay/ecommerce/responses/__init__.py
sipay/ecommerce/responses/authorization.py
sipay/ecommerce/responses/cancellation.py
sipay/ecommerce/responses/card.py
sipay/ecommerce/responses/confirmation.py
sipay/ecommerce/responses/preauthorization.py
sipay/ecommerce/responses/query.py
sipay/ecommerce/responses/refund.py
sipay/ecommerce/responses/register.py
sipay/ecommerce/responses/transaction.py
sipay/ecommerce/responses/unlock.py
sipay/ecommerce/responses/unregister.py
sipay/paymethod/__init__.py
sipay/paymethod/card.py
sipay/paymethod/fastpay.py
sipay/paymethod/storedcard.py
sipay/utils/__init__.py
sipay-1.1.0.dist-info/METADATA
sipay-1.1.0.dist-info/RECORD
sipay-1.1.0.dist-info/WHEEL
sipay-1.1.0.dist-info/top_level.txt
