Metadata-Version: 2.1
Name: sipay
Version: 1.1.0
Summary: Python SDK
Home-page: https://github.com/sipay/python-sdk
Author: Sipay Plus SL
Author-email: develop@sipay.es
License: UNKNOWN
Download-URL: https://github.com/sipay/python-sdk
Platform: linux
Classifier: Development Status :: 5 - Production/Stable
Classifier: Programming Language :: Python :: 3.4
Classifier: Programming Language :: Python :: 3.5
Classifier: Programming Language :: Python :: 3.6
Requires-Python: >=3.4
Requires-Dist: certifi (==2017.11.5)
Requires-Dist: chardet (==3.0.4)
Requires-Dist: idna (==2.6)
Requires-Dist: requests (==2.18.4)
Requires-Dist: urllib3 (==1.22)
